jznsearch/__init__.py
jznsearch/version.py
jznsearch-0.1.6.dist-info/LICENSE.txt
jznsearch-0.1.6.dist-info/METADATA
jznsearch-0.1.6.dist-info/WHEEL
jznsearch-0.1.6.dist-info/entry_points.txt
jznsearch-0.1.6.dist-info/top_level.txt
jznsearch-0.1.6.dist-info/RECORD
