Metadata-Version: 2.1
Name: jznsearch
Version: 0.1.6
Summary: Simple search in JSON files
Home-page: https://github.com/jsanotheraccount/jznsearch
Author: Jane Skvortsova
Author-email: jane.skvortsova@gmail.com
License: MIT
Platform: UNKNOWN
Classifier: License :: OSI Approved :: MIT License
Classifier: Programming Language :: Python :: 3
Classifier: Programming Language :: Python :: 3.7
